eval/__init__.py
eval/auto_llms_eval.py
eval/commands/__init__.py
eval/commands/auto_eval.py
eval/prompt_template/__init__.py
eval/prompt_template/prompter.py
eval/prompt_template/prompts.py
eval/utils/__init__.py
eval/utils/data_utils.py
auto_eval-0.4.3.dist-info/LICENSE
auto_eval-0.4.3.dist-info/METADATA
auto_eval-0.4.3.dist-info/WHEEL
auto_eval-0.4.3.dist-info/entry_points.txt
auto_eval-0.4.3.dist-info/top_level.txt
auto_eval-0.4.3.dist-info/RECORD
