Metadata-Version: 2.1
Name: auto-eval
Version: 0.4.3
Summary: Using only one line of commmands to evaluate multiple models
Home-page: https://github.com/muximus3/Auto-Eval
Classifier: Development Status :: 3 - Alpha
Classifier: License :: OSI Approved :: MIT License
Classifier: Programming Language :: Python :: 3
Classifier: Operating System :: OS Independent
License-File: LICENSE
Requires-Dist: one-api-tool
Requires-Dist: pandas
Requires-Dist: openpyxl
Requires-Dist: tabulate
Requires-Dist: XlsxWriter
